mlflow_cortex/__init__.py
mlflow_cortex-1.10.0.dist-info/METADATA
mlflow_cortex-1.10.0.dist-info/WHEEL
mlflow_cortex-1.10.0.dist-info/top_level.txt
mlflow_cortex-1.10.0.dist-info/RECORD
